[{"line":1,"type":"line","surahNumber":"18","surah":"الكهف","index":null,"ayah":"46","text":[{"id":"43099","char_type":"word","text":"الْمَالُ","aya":"46","sura":"18","audio":"018/018_046_001.mp3"},{"id":"43100","char_type":"word","text":"وَالْبَنُونَ","aya":"46","sura":"18","audio":"018/018_046_002.mp3"},{"id":"43101","char_type":"word","text":"زِينَةُ","aya":"46","sura":"18","audio":"018/018_046_003.mp3"},{"id":"43102","char_type":"word","text":"الْحَيَاةِ","aya":"46","sura":"18","audio":"018/018_046_004.mp3"},{"id":"43103","char_type":"word","text":"الدُّنْيَا","aya":"46","sura":"18","audio":"018/018_046_005.mp3"},{"id":"43104","char_type":"pause","text":"ۖ","aya":"46","sura":"18","audio":null},{"id":"43105","char_type":"word","text":"وَالْبَاقِيَاتُ","aya":"46","sura":"18","audio":"018/018_046_007.mp3"},{"id":"43106","char_type":"word","text":"الصَّالِحَاتُ","aya":"46","sura":"18","audio":"018/018_046_008.mp3"}],"lineId":4457},{"line":2,"type":"line","surahNumber":"18","surah":"الكهف","index":null,"ayah":"46","text":[{"id":"43107","char_type":"word","text":"خَيْرٌ","aya":"46","sura":"18","audio":"018/018_046_009.mp3"},{"id":"43108","char_type":"word","text":"عِنْدَ","aya":"46","sura":"18","audio":"018/018_046_010.mp3"},{"id":"43109","char_type":"word","text":"رَبِّكَ","aya":"46","sura":"18","audio":"018/018_046_011.mp3"},{"id":"43110","char_type":"word","text":"ثَوَابًا","aya":"46","sura":"18","audio":"018/018_046_012.mp3"},{"id":"43111","char_type":"word","text":"وَخَيْرٌ","aya":"46","sura":"18","audio":"018/018_046_013.mp3"},{"id":"43112","char_type":"word","text":"أَمَلًا","aya":"46","sura":"18","audio":"018/018_046_014.mp3"},{"id":"43113","char_type":"end","text":null,"aya":"46","sura":"18","audio":"018046.mp3"},{"id":"43114","char_type":"word","text":"وَيَوْمَ","aya":"47","sura":"18","audio":"018/018_047_001.mp3"},{"id":"43115","char_type":"word","text":"نُسَيِّرُ","aya":"47","sura":"18","audio":"018/018_047_002.mp3"},{"id":"43116","char_type":"word","text":"الْجِبَالَ","aya":"47","sura":"18","audio":"018/018_047_003.mp3"},{"id":"43117","char_type":"word","text":"وَتَرَى","aya":"47","sura":"18","audio":"018/018_047_004.mp3"}],"lineId":4458},{"line":3,"type":"line","surahNumber":"18","surah":"الكهف","index":null,"ayah":"47","text":[{"id":"43118","char_type":"word","text":"الْأَرْضَ","aya":"47","sura":"18","audio":"018/018_047_005.mp3"},{"id":"43119","char_type":"word","text":"بَارِزَةً","aya":"47","sura":"18","audio":"018/018_047_006.mp3"},{"id":"43120","char_type":"word","text":"وَحَشَرْنَاهُمْ","aya":"47","sura":"18","audio":"018/018_047_007.mp3"},{"id":"43121","char_type":"word","text":"فَلَمْ","aya":"47","sura":"18","audio":"018/018_047_008.mp3"},{"id":"43122","char_type":"word","text":"نُغَادِرْ","aya":"47","sura":"18","audio":"018/018_047_009.mp3"},{"id":"43123","char_type":"word","text":"مِنْهُمْ","aya":"47","sura":"18","audio":"018/018_047_010.mp3"},{"id":"43124","char_type":"word","text":"أَحَدًا","aya":"47","sura":"18","audio":"018/018_047_011.mp3"},{"id":"43125","char_type":"end","text":null,"aya":"47","sura":"18","audio":"018047.mp3"},{"id":"43126","char_type":"word","text":"وَعُرِضُوا","aya":"48","sura":"18","audio":"018/018_048_001.mp3"}],"lineId":4459},{"line":4,"type":"line","surahNumber":"18","surah":"الكهف","index":null,"ayah":"48","text":[{"id":"43127","char_type":"word","text":"عَلَىٰ","aya":"48","sura":"18","audio":"018/018_048_002.mp3"},{"id":"43128","char_type":"word","text":"رَبِّكَ","aya":"48","sura":"18","audio":"018/018_048_003.mp3"},{"id":"43129","char_type":"word","text":"صَفًّا","aya":"48","sura":"18","audio":"018/018_048_004.mp3"},{"id":"43130","char_type":"word","text":"لَقَدْ","aya":"48","sura":"18","audio":"018/018_048_005.mp3"},{"id":"43131","char_type":"word","text":"جِئْتُمُونَا","aya":"48","sura":"18","audio":"018/018_048_006.mp3"},{"id":"43132","char_type":"word","text":"كَمَا","aya":"48","sura":"18","audio":"018/018_048_007.mp3"},{"id":"43133","char_type":"word","text":"خَلَقْنَاكُمْ","aya":"48","sura":"18","audio":"018/018_048_008.mp3"},{"id":"43134","char_type":"word","text":"أَوَّلَ","aya":"48","sura":"18","audio":"018/018_048_009.mp3"},{"id":"43135","char_type":"word","text":"مَرَّةٍ","aya":"48","sura":"18","audio":"018/018_048_010.mp3"},{"id":"43136","char_type":"pause","text":"ۚ","aya":"48","sura":"18","audio":null},{"id":"43137","char_type":"word","text":"بَلْ","aya":"48","sura":"18","audio":"018/018_048_012.mp3"},{"id":"43138","char_type":"word","text":"زَعَمْتُمْ","aya":"48","sura":"18","audio":"018/018_048_013.mp3"}],"lineId":4460},{"line":5,"type":"line","surahNumber":"18","surah":"الكهف","index":null,"ayah":"48","text":[{"id":"43139","char_type":"word","text":"أَلَّنْ","aya":"48","sura":"18","audio":"018/018_048_014.mp3"},{"id":"43140","char_type":"word","text":"نَجْعَلَ","aya":"48","sura":"18","audio":"018/018_048_015.mp3"},{"id":"43141","char_type":"word","text":"لَكُمْ","aya":"48","sura":"18","audio":"018/018_048_016.mp3"},{"id":"43142","char_type":"word","text":"مَوْعِدًا","aya":"48","sura":"18","audio":"018/018_048_017.mp3"},{"id":"43143","char_type":"end","text":null,"aya":"48","sura":"18","audio":"018048.mp3"},{"id":"43144","char_type":"word","text":"وَوُضِعَ","aya":"49","sura":"18","audio":"018/018_049_001.mp3"},{"id":"43145","char_type":"word","text":"الْكِتَابُ","aya":"49","sura":"18","audio":"018/018_049_002.mp3"},{"id":"43146","char_type":"word","text":"فَتَرَى","aya":"49","sura":"18","audio":"018/018_049_003.mp3"},{"id":"43147","char_type":"word","text":"الْمُجْرِمِينَ","aya":"49","sura":"18","audio":"018/018_049_004.mp3"}],"lineId":4461},{"line":6,"type":"line","surahNumber":"18","surah":"الكهف","index":null,"ayah":"49","text":[{"id":"43148","char_type":"word","text":"مُشْفِقِينَ","aya":"49","sura":"18","audio":"018/018_049_005.mp3"},{"id":"43149","char_type":"word","text":"مِمَّا","aya":"49","sura":"18","audio":"018/018_049_006.mp3"},{"id":"43150","char_type":"word","text":"فِيهِ","aya":"49","sura":"18","audio":"018/018_049_007.mp3"},{"id":"43151","char_type":"word","text":"وَيَقُولُونَ","aya":"49","sura":"18","audio":"018/018_049_008.mp3"},{"id":"43152","char_type":"word","text":"يَا وَيْلَتَنَا","aya":"49","sura":"18","audio":"018/018_049_009.mp3"},{"id":"43153","char_type":"word","text":"مَالِ","aya":"49","sura":"18","audio":"018/018_049_010.mp3"},{"id":"43154","char_type":"word","text":"هَٰذَا","aya":"49","sura":"18","audio":"018/018_049_011.mp3"},{"id":"43155","char_type":"word","text":"الْكِتَابِ","aya":"49","sura":"18","audio":"018/018_049_012.mp3"}],"lineId":4462},{"line":7,"type":"line","surahNumber":"18","surah":"الكهف","index":null,"ayah":"49","text":[{"id":"43156","char_type":"word","text":"لَا","aya":"49","sura":"18","audio":"018/018_049_013.mp3"},{"id":"43157","char_type":"word","text":"يُغَادِرُ","aya":"49","sura":"18","audio":"018/018_049_014.mp3"},{"id":"43158","char_type":"word","text":"صَغِيرَةً","aya":"49","sura":"18","audio":"018/018_049_015.mp3"},{"id":"43159","char_type":"word","text":"وَلَا","aya":"49","sura":"18","audio":"018/018_049_016.mp3"},{"id":"43160","char_type":"word","text":"كَبِيرَةً","aya":"49","sura":"18","audio":"018/018_049_017.mp3"},{"id":"43161","char_type":"word","text":"إِلَّا","aya":"49","sura":"18","audio":"018/018_049_018.mp3"},{"id":"43162","char_type":"word","text":"أَحْصَاهَا","aya":"49","sura":"18","audio":"018/018_049_019.mp3"},{"id":"43163","char_type":"pause","text":"ۚ","aya":"49","sura":"18","audio":null},{"id":"43164","char_type":"word","text":"وَوَجَدُوا","aya":"49","sura":"18","audio":"018/018_049_021.mp3"},{"id":"43165","char_type":"word","text":"مَا","aya":"49","sura":"18","audio":"018/018_049_022.mp3"},{"id":"43166","char_type":"word","text":"عَمِلُوا","aya":"49","sura":"18","audio":"018/018_049_023.mp3"}],"lineId":4463},{"line":8,"type":"line","surahNumber":"18","surah":"الكهف","index":null,"ayah":"49","text":[{"id":"43167","char_type":"word","text":"حَاضِرًا","aya":"49","sura":"18","audio":"018/018_049_024.mp3"},{"id":"43168","char_type":"pause","text":"ۗ","aya":"49","sura":"18","audio":null},{"id":"43169","char_type":"word","text":"وَلَا","aya":"49","sura":"18","audio":"018/018_049_026.mp3"},{"id":"43170","char_type":"word","text":"يَظْلِمُ","aya":"49","sura":"18","audio":"018/018_049_027.mp3"},{"id":"43171","char_type":"word","text":"رَبُّكَ","aya":"49","sura":"18","audio":"018/018_049_028.mp3"},{"id":"43172","char_type":"word","text":"أَحَدًا","aya":"49","sura":"18","audio":"018/018_049_029.mp3"},{"id":"43173","char_type":"end","text":null,"aya":"49","sura":"18","audio":"018049.mp3"},{"id":"43174","char_type":"word","text":"وَإِذْ","aya":"50","sura":"18","audio":"018/018_050_001.mp3"},{"id":"43175","char_type":"word","text":"قُلْنَا","aya":"50","sura":"18","audio":"018/018_050_002.mp3"},{"id":"43176","char_type":"word","text":"لِلْمَلَائِكَةِ","aya":"50","sura":"18","audio":"018/018_050_003.mp3"},{"id":"43177","char_type":"word","text":"اسْجُدُوا","aya":"50","sura":"18","audio":"018/018_050_004.mp3"}],"lineId":4464},{"line":9,"type":"line","surahNumber":"18","surah":"الكهف","index":null,"ayah":"50","text":[{"id":"43178","char_type":"word","text":"لِآدَمَ","aya":"50","sura":"18","audio":"018/018_050_005.mp3"},{"id":"43179","char_type":"word","text":"فَسَجَدُوا","aya":"50","sura":"18","audio":"018/018_050_006.mp3"},{"id":"43180","char_type":"word","text":"إِلَّا","aya":"50","sura":"18","audio":"018/018_050_007.mp3"},{"id":"43181","char_type":"word","text":"إِبْلِيسَ","aya":"50","sura":"18","audio":"018/018_050_008.mp3"},{"id":"43182","char_type":"word","text":"كَانَ","aya":"50","sura":"18","audio":"018/018_050_009.mp3"},{"id":"43183","char_type":"word","text":"مِنَ","aya":"50","sura":"18","audio":"018/018_050_010.mp3"},{"id":"43184","char_type":"word","text":"الْجِنِّ","aya":"50","sura":"18","audio":"018/018_050_011.mp3"},{"id":"43185","char_type":"word","text":"فَفَسَقَ","aya":"50","sura":"18","audio":"018/018_050_012.mp3"},{"id":"43186","char_type":"word","text":"عَنْ","aya":"50","sura":"18","audio":"018/018_050_013.mp3"},{"id":"43187","char_type":"word","text":"أَمْرِ","aya":"50","sura":"18","audio":"018/018_050_014.mp3"},{"id":"43188","char_type":"word","text":"رَبِّهِ","aya":"50","sura":"18","audio":"018/018_050_015.mp3"},{"id":"43189","char_type":"pause","text":"ۗ","aya":"50","sura":"18","audio":null}],"lineId":4465},{"line":10,"type":"line","surahNumber":"18","surah":"الكهف","index":null,"ayah":"50","text":[{"id":"43190","char_type":"word","text":"أَفَتَتَّخِذُونَهُ","aya":"50","sura":"18","audio":"018/018_050_017.mp3"},{"id":"43191","char_type":"word","text":"وَذُرِّيَّتَهُ","aya":"50","sura":"18","audio":"018/018_050_018.mp3"},{"id":"43192","char_type":"word","text":"أَوْلِيَاءَ","aya":"50","sura":"18","audio":"018/018_050_019.mp3"},{"id":"43193","char_type":"word","text":"مِنْ","aya":"50","sura":"18","audio":"018/018_050_020.mp3"},{"id":"43194","char_type":"word","text":"دُونِي","aya":"50","sura":"18","audio":"018/018_050_021.mp3"},{"id":"43195","char_type":"word","text":"وَهُمْ","aya":"50","sura":"18","audio":"018/018_050_022.mp3"},{"id":"43196","char_type":"word","text":"لَكُمْ","aya":"50","sura":"18","audio":"018/018_050_023.mp3"},{"id":"43197","char_type":"word","text":"عَدُوٌّ","aya":"50","sura":"18","audio":"018/018_050_024.mp3"},{"id":"43198","char_type":"pause","text":"ۚ","aya":"50","sura":"18","audio":null}],"lineId":4466},{"line":11,"type":"line","surahNumber":"18","surah":"الكهف","index":null,"ayah":"50","text":[{"id":"43199","char_type":"word","text":"بِئْسَ","aya":"50","sura":"18","audio":"018/018_050_026.mp3"},{"id":"43200","char_type":"word","text":"لِلظَّالِمِينَ","aya":"50","sura":"18","audio":"018/018_050_027.mp3"},{"id":"43201","char_type":"word","text":"بَدَلًا","aya":"50","sura":"18","audio":"018/018_050_028.mp3"},{"id":"43202","char_type":"end","text":null,"aya":"50","sura":"18","audio":"018050.mp3"},{"id":"43203","char_type":"rub-el-hizb","text":"۞","aya":"51","sura":"18","audio":null},{"id":"43204","char_type":"word","text":"مَا","aya":"51","sura":"18","audio":"018/018_051_002.mp3"},{"id":"43205","char_type":"word","text":"أَشْهَدْتُهُمْ","aya":"51","sura":"18","audio":"018/018_051_003.mp3"},{"id":"43206","char_type":"word","text":"خَلْقَ","aya":"51","sura":"18","audio":"018/018_051_004.mp3"},{"id":"43207","char_type":"word","text":"السَّمَاوَاتِ","aya":"51","sura":"18","audio":"018/018_051_005.mp3"}],"lineId":4467},{"line":12,"type":"line","surahNumber":"18","surah":"الكهف","index":null,"ayah":"51","text":[{"id":"43208","char_type":"word","text":"وَالْأَرْضِ","aya":"51","sura":"18","audio":"018/018_051_006.mp3"},{"id":"43209","char_type":"word","text":"وَلَا","aya":"51","sura":"18","audio":"018/018_051_007.mp3"},{"id":"43210","char_type":"word","text":"خَلْقَ","aya":"51","sura":"18","audio":"018/018_051_008.mp3"},{"id":"43211","char_type":"word","text":"أَنْفُسِهِمْ","aya":"51","sura":"18","audio":"018/018_051_009.mp3"},{"id":"43212","char_type":"word","text":"وَمَا","aya":"51","sura":"18","audio":"018/018_051_010.mp3"},{"id":"43213","char_type":"word","text":"كُنْتُ","aya":"51","sura":"18","audio":"018/018_051_011.mp3"},{"id":"43214","char_type":"word","text":"مُتَّخِذَ","aya":"51","sura":"18","audio":"018/018_051_012.mp3"},{"id":"43215","char_type":"word","text":"الْمُضِلِّينَ","aya":"51","sura":"18","audio":"018/018_051_013.mp3"},{"id":"43216","char_type":"word","text":"عَضُدًا","aya":"51","sura":"18","audio":"018/018_051_014.mp3"}],"lineId":4468},{"line":13,"type":"line","surahNumber":"18","surah":"الكهف","index":null,"ayah":"51","text":[{"id":"43217","char_type":"end","text":null,"aya":"51","sura":"18","audio":"018051.mp3"},{"id":"43218","char_type":"word","text":"وَيَوْمَ","aya":"52","sura":"18","audio":"018/018_052_001.mp3"},{"id":"43219","char_type":"word","text":"يَقُولُ","aya":"52","sura":"18","audio":"018/018_052_002.mp3"},{"id":"43220","char_type":"word","text":"نَادُوا","aya":"52","sura":"18","audio":"018/018_052_003.mp3"},{"id":"43221","char_type":"word","text":"شُرَكَائِيَ","aya":"52","sura":"18","audio":"018/018_052_004.mp3"},{"id":"43222","char_type":"word","text":"الَّذِينَ","aya":"52","sura":"18","audio":"018/018_052_005.mp3"},{"id":"43223","char_type":"word","text":"زَعَمْتُمْ","aya":"52","sura":"18","audio":"018/018_052_006.mp3"},{"id":"43224","char_type":"word","text":"فَدَعَوْهُمْ","aya":"52","sura":"18","audio":"018/018_052_007.mp3"}],"lineId":4469},{"line":14,"type":"line","surahNumber":"18","surah":"الكهف","index":null,"ayah":"52","text":[{"id":"43225","char_type":"word","text":"فَلَمْ","aya":"52","sura":"18","audio":"018/018_052_008.mp3"},{"id":"43226","char_type":"word","text":"يَسْتَجِيبُوا","aya":"52","sura":"18","audio":"018/018_052_009.mp3"},{"id":"43227","char_type":"word","text":"لَهُمْ","aya":"52","sura":"18","audio":"018/018_052_010.mp3"},{"id":"43228","char_type":"word","text":"وَجَعَلْنَا","aya":"52","sura":"18","audio":"018/018_052_011.mp3"},{"id":"43229","char_type":"word","text":"بَيْنَهُمْ","aya":"52","sura":"18","audio":"018/018_052_012.mp3"},{"id":"43230","char_type":"word","text":"مَوْبِقًا","aya":"52","sura":"18","audio":"018/018_052_013.mp3"},{"id":"43231","char_type":"end","text":null,"aya":"52","sura":"18","audio":"018052.mp3"},{"id":"43232","char_type":"word","text":"وَرَأَى","aya":"53","sura":"18","audio":"018/018_053_001.mp3"},{"id":"43233","char_type":"word","text":"الْمُجْرِمُونَ","aya":"53","sura":"18","audio":"018/018_053_002.mp3"}],"lineId":4470},{"line":15,"type":"line","surahNumber":"18","surah":"الكهف","index":null,"ayah":"53","text":[{"id":"43234","char_type":"word","text":"النَّارَ","aya":"53","sura":"18","audio":"018/018_053_003.mp3"},{"id":"43235","char_type":"word","text":"فَظَنُّوا","aya":"53","sura":"18","audio":"018/018_053_004.mp3"},{"id":"43236","char_type":"word","text":"أَنَّهُمْ","aya":"53","sura":"18","audio":"018/018_053_005.mp3"},{"id":"43237","char_type":"word","text":"مُوَاقِعُوهَا","aya":"53","sura":"18","audio":"018/018_053_006.mp3"},{"id":"43238","char_type":"word","text":"وَلَمْ","aya":"53","sura":"18","audio":"018/018_053_007.mp3"},{"id":"43239","char_type":"word","text":"يَجِدُوا","aya":"53","sura":"18","audio":"018/018_053_008.mp3"},{"id":"43240","char_type":"word","text":"عَنْهَا","aya":"53","sura":"18","audio":"018/018_053_009.mp3"},{"id":"43241","char_type":"word","text":"مَصْرِفًا","aya":"53","sura":"18","audio":"018/018_053_010.mp3"},{"id":"43242","char_type":"end","text":null,"aya":"53","sura":"18","audio":"018053.mp3"}],"lineId":4471}]