[{"line":1,"type":"line","surahNumber":"70","surah":"المعارج","index":null,"ayah":"40","text":[{"id":"83458","char_type":"word","text":"فَلَا","aya":"40","sura":"70","audio":"070/070_040_001.mp3"},{"id":"83459","char_type":"word","text":"أُقْسِمُ","aya":"40","sura":"70","audio":"070/070_040_002.mp3"},{"id":"83460","char_type":"word","text":"بِرَبِّ","aya":"40","sura":"70","audio":"070/070_040_003.mp3"},{"id":"83461","char_type":"word","text":"الْمَشَارِقِ","aya":"40","sura":"70","audio":"070/070_040_004.mp3"},{"id":"83462","char_type":"word","text":"وَالْمَغَارِبِ","aya":"40","sura":"70","audio":"070/070_040_005.mp3"},{"id":"83463","char_type":"word","text":"إِنَّا","aya":"40","sura":"70","audio":"070/070_040_006.mp3"},{"id":"83464","char_type":"word","text":"لَقَادِرُونَ","aya":"40","sura":"70","audio":"070/070_040_007.mp3"},{"id":"83465","char_type":"end","text":null,"aya":"40","sura":"70","audio":"070040.mp3"},{"id":"83466","char_type":"word","text":"عَلَىٰ","aya":"41","sura":"70","audio":"070/070_041_001.mp3"},{"id":"83467","char_type":"word","text":"أَنْ","aya":"41","sura":"70","audio":"070/070_041_002.mp3"},{"id":"83468","char_type":"word","text":"نُبَدِّلَ","aya":"41","sura":"70","audio":"070/070_041_003.mp3"},{"id":"83469","char_type":"word","text":"خَيْرًا","aya":"41","sura":"70","audio":"070/070_041_004.mp3"},{"id":"83470","char_type":"word","text":"مِنْهُمْ","aya":"41","sura":"70","audio":"070/070_041_005.mp3"}],"lineId":8522},{"line":2,"type":"line","surahNumber":"70","surah":"المعارج","index":null,"ayah":"41","text":[{"id":"83471","char_type":"word","text":"وَمَا","aya":"41","sura":"70","audio":"070/070_041_006.mp3"},{"id":"83472","char_type":"word","text":"نَحْنُ","aya":"41","sura":"70","audio":"070/070_041_007.mp3"},{"id":"83473","char_type":"word","text":"بِمَسْبُوقِينَ","aya":"41","sura":"70","audio":"070/070_041_008.mp3"},{"id":"83474","char_type":"end","text":null,"aya":"41","sura":"70","audio":"070041.mp3"},{"id":"83475","char_type":"word","text":"فَذَرْهُمْ","aya":"42","sura":"70","audio":"070/070_042_001.mp3"},{"id":"83476","char_type":"word","text":"يَخُوضُوا","aya":"42","sura":"70","audio":"070/070_042_002.mp3"},{"id":"83477","char_type":"word","text":"وَيَلْعَبُوا","aya":"42","sura":"70","audio":"070/070_042_003.mp3"},{"id":"83478","char_type":"word","text":"حَتَّىٰ","aya":"42","sura":"70","audio":"070/070_042_004.mp3"},{"id":"83479","char_type":"word","text":"يُلَاقُوا","aya":"42","sura":"70","audio":"070/070_042_005.mp3"},{"id":"83480","char_type":"word","text":"يَوْمَهُمُ","aya":"42","sura":"70","audio":"070/070_042_006.mp3"},{"id":"83481","char_type":"word","text":"الَّذِي","aya":"42","sura":"70","audio":"070/070_042_007.mp3"}],"lineId":8523},{"line":3,"type":"line","surahNumber":"70","surah":"المعارج","index":null,"ayah":"42","text":[{"id":"83482","char_type":"word","text":"يُوعَدُونَ","aya":"42","sura":"70","audio":"070/070_042_008.mp3"},{"id":"83483","char_type":"end","text":null,"aya":"42","sura":"70","audio":"070042.mp3"},{"id":"83484","char_type":"word","text":"يَوْمَ","aya":"43","sura":"70","audio":"070/070_043_001.mp3"},{"id":"83485","char_type":"word","text":"يَخْرُجُونَ","aya":"43","sura":"70","audio":"070/070_043_002.mp3"},{"id":"83486","char_type":"word","text":"مِنَ","aya":"43","sura":"70","audio":"070/070_043_003.mp3"},{"id":"83487","char_type":"word","text":"الْأَجْدَاثِ","aya":"43","sura":"70","audio":"070/070_043_004.mp3"},{"id":"83488","char_type":"word","text":"سِرَاعًا","aya":"43","sura":"70","audio":"070/070_043_005.mp3"},{"id":"83489","char_type":"word","text":"كَأَنَّهُمْ","aya":"43","sura":"70","audio":"070/070_043_006.mp3"},{"id":"83490","char_type":"word","text":"إِلَىٰ","aya":"43","sura":"70","audio":"070/070_043_007.mp3"},{"id":"83491","char_type":"word","text":"نُصُبٍ","aya":"43","sura":"70","audio":"070/070_043_008.mp3"},{"id":"83492","char_type":"word","text":"يُوفِضُونَ","aya":"43","sura":"70","audio":"070/070_043_009.mp3"}],"lineId":8524},{"line":4,"type":"line","surahNumber":"70","surah":"المعارج","index":null,"ayah":"43","text":[{"id":"83493","char_type":"end","text":null,"aya":"43","sura":"70","audio":"070043.mp3"},{"id":"83494","char_type":"word","text":"خَاشِعَةً","aya":"44","sura":"70","audio":"070/070_044_001.mp3"},{"id":"83495","char_type":"word","text":"أَبْصَارُهُمْ","aya":"44","sura":"70","audio":"070/070_044_002.mp3"},{"id":"83496","char_type":"word","text":"تَرْهَقُهُمْ","aya":"44","sura":"70","audio":"070/070_044_003.mp3"},{"id":"83497","char_type":"word","text":"ذِلَّةٌ","aya":"44","sura":"70","audio":"070/070_044_004.mp3"},{"id":"83498","char_type":"pause","text":"ۚ","aya":"44","sura":"70","audio":null},{"id":"83499","char_type":"word","text":"ذَٰلِكَ","aya":"44","sura":"70","audio":"070/070_044_006.mp3"},{"id":"83500","char_type":"word","text":"الْيَوْمُ","aya":"44","sura":"70","audio":"070/070_044_007.mp3"},{"id":"83501","char_type":"word","text":"الَّذِي","aya":"44","sura":"70","audio":"070/070_044_008.mp3"},{"id":"83502","char_type":"word","text":"كَانُوا","aya":"44","sura":"70","audio":"070/070_044_009.mp3"},{"id":"83503","char_type":"word","text":"يُوعَدُونَ","aya":"44","sura":"70","audio":"070/070_044_010.mp3"},{"id":"83504","char_type":"end","text":null,"aya":"44","sura":"70","audio":"070044.mp3"}],"lineId":8525},{"type":"start_sura","surah":"نوح","index":"71","name":"نوح","lineId":8526},{"line":6,"type":"besmellah","surah":"","lineId":8527},{"line":7,"type":"line","surahNumber":"71","surah":"نوح","index":null,"ayah":"1","text":[{"id":"83505","char_type":"word","text":"إِنَّا","aya":"1","sura":"71","audio":"071/071_001_001.mp3"},{"id":"83506","char_type":"word","text":"أَرْسَلْنَا","aya":"1","sura":"71","audio":"071/071_001_002.mp3"},{"id":"83507","char_type":"word","text":"نُوحًا","aya":"1","sura":"71","audio":"071/071_001_003.mp3"},{"id":"83508","char_type":"word","text":"إِلَىٰ","aya":"1","sura":"71","audio":"071/071_001_004.mp3"},{"id":"83509","char_type":"word","text":"قَوْمِهِ","aya":"1","sura":"71","audio":"071/071_001_005.mp3"},{"id":"83510","char_type":"word","text":"أَنْ","aya":"1","sura":"71","audio":"071/071_001_006.mp3"},{"id":"83511","char_type":"word","text":"أَنْذِرْ","aya":"1","sura":"71","audio":"071/071_001_007.mp3"},{"id":"83512","char_type":"word","text":"قَوْمَكَ","aya":"1","sura":"71","audio":"071/071_001_008.mp3"},{"id":"83513","char_type":"word","text":"مِنْ","aya":"1","sura":"71","audio":"071/071_001_009.mp3"},{"id":"83514","char_type":"word","text":"قَبْلِ","aya":"1","sura":"71","audio":"071/071_001_010.mp3"},{"id":"83515","char_type":"word","text":"أَنْ","aya":"1","sura":"71","audio":"071/071_001_011.mp3"},{"id":"83516","char_type":"word","text":"يَأْتِيَهُمْ","aya":"1","sura":"71","audio":"071/071_001_012.mp3"}],"lineId":8528},{"line":8,"type":"line","surahNumber":"71","surah":"نوح","index":null,"ayah":"1","text":[{"id":"83517","char_type":"word","text":"عَذَابٌ","aya":"1","sura":"71","audio":"071/071_001_013.mp3"},{"id":"83518","char_type":"word","text":"أَلِيمٌ","aya":"1","sura":"71","audio":"071/071_001_014.mp3"},{"id":"83519","char_type":"end","text":null,"aya":"1","sura":"71","audio":"071001.mp3"},{"id":"83520","char_type":"word","text":"قَالَ","aya":"2","sura":"71","audio":"071/071_002_001.mp3"},{"id":"83521","char_type":"word","text":"يَا قَوْمِ","aya":"2","sura":"71","audio":"071/071_002_002.mp3"},{"id":"83522","char_type":"word","text":"إِنِّي","aya":"2","sura":"71","audio":"071/071_002_003.mp3"},{"id":"83523","char_type":"word","text":"لَكُمْ","aya":"2","sura":"71","audio":"071/071_002_004.mp3"},{"id":"83524","char_type":"word","text":"نَذِيرٌ","aya":"2","sura":"71","audio":"071/071_002_005.mp3"},{"id":"83525","char_type":"word","text":"مُبِينٌ","aya":"2","sura":"71","audio":"071/071_002_006.mp3"},{"id":"83526","char_type":"end","text":null,"aya":"2","sura":"71","audio":"071002.mp3"},{"id":"83527","char_type":"word","text":"أَنِ","aya":"3","sura":"71","audio":"071/071_003_001.mp3"},{"id":"83528","char_type":"word","text":"اعْبُدُوا","aya":"3","sura":"71","audio":"071/071_003_002.mp3"}],"lineId":8529},{"line":9,"type":"line","surahNumber":"71","surah":"نوح","index":null,"ayah":"3","text":[{"id":"83529","char_type":"word","text":"اللَّهَ","aya":"3","sura":"71","audio":"071/071_003_003.mp3"},{"id":"83530","char_type":"word","text":"وَاتَّقُوهُ","aya":"3","sura":"71","audio":"071/071_003_004.mp3"},{"id":"83531","char_type":"word","text":"وَأَطِيعُونِ","aya":"3","sura":"71","audio":"071/071_003_005.mp3"},{"id":"83532","char_type":"end","text":null,"aya":"3","sura":"71","audio":"071003.mp3"},{"id":"83533","char_type":"word","text":"يَغْفِرْ","aya":"4","sura":"71","audio":"071/071_004_001.mp3"},{"id":"83534","char_type":"word","text":"لَكُمْ","aya":"4","sura":"71","audio":"071/071_004_002.mp3"},{"id":"83535","char_type":"word","text":"مِنْ","aya":"4","sura":"71","audio":"071/071_004_003.mp3"},{"id":"83536","char_type":"word","text":"ذُنُوبِكُمْ","aya":"4","sura":"71","audio":"071/071_004_004.mp3"},{"id":"83537","char_type":"word","text":"وَيُؤَخِّرْكُمْ","aya":"4","sura":"71","audio":"071/071_004_005.mp3"}],"lineId":8530},{"line":10,"type":"line","surahNumber":"71","surah":"نوح","index":null,"ayah":"4","text":[{"id":"83538","char_type":"word","text":"إِلَىٰ","aya":"4","sura":"71","audio":"071/071_004_006.mp3"},{"id":"83539","char_type":"word","text":"أَجَلٍ","aya":"4","sura":"71","audio":"071/071_004_007.mp3"},{"id":"83540","char_type":"word","text":"مُسَمًّى","aya":"4","sura":"71","audio":"071/071_004_008.mp3"},{"id":"83541","char_type":"pause","text":"ۚ","aya":"4","sura":"71","audio":null},{"id":"83542","char_type":"word","text":"إِنَّ","aya":"4","sura":"71","audio":"071/071_004_010.mp3"},{"id":"83543","char_type":"word","text":"أَجَلَ","aya":"4","sura":"71","audio":"071/071_004_011.mp3"},{"id":"83544","char_type":"word","text":"اللَّهِ","aya":"4","sura":"71","audio":"071/071_004_012.mp3"},{"id":"83545","char_type":"word","text":"إِذَا","aya":"4","sura":"71","audio":"071/071_004_013.mp3"},{"id":"83546","char_type":"word","text":"جَاءَ","aya":"4","sura":"71","audio":"071/071_004_014.mp3"},{"id":"83547","char_type":"word","text":"لَا","aya":"4","sura":"71","audio":"071/071_004_015.mp3"},{"id":"83548","char_type":"word","text":"يُؤَخَّرُ","aya":"4","sura":"71","audio":"071/071_004_016.mp3"},{"id":"83549","char_type":"pause","text":"ۖ","aya":"4","sura":"71","audio":null},{"id":"83550","char_type":"word","text":"لَوْ","aya":"4","sura":"71","audio":"071/071_004_018.mp3"},{"id":"83551","char_type":"word","text":"كُنْتُمْ","aya":"4","sura":"71","audio":"071/071_004_019.mp3"},{"id":"83552","char_type":"word","text":"تَعْلَمُونَ","aya":"4","sura":"71","audio":"071/071_004_020.mp3"}],"lineId":8531},{"line":11,"type":"line","surahNumber":"71","surah":"نوح","index":null,"ayah":"4","text":[{"id":"83553","char_type":"end","text":null,"aya":"4","sura":"71","audio":"071004.mp3"},{"id":"83554","char_type":"word","text":"قَالَ","aya":"5","sura":"71","audio":"071/071_005_001.mp3"},{"id":"83555","char_type":"word","text":"رَبِّ","aya":"5","sura":"71","audio":"071/071_005_002.mp3"},{"id":"83556","char_type":"word","text":"إِنِّي","aya":"5","sura":"71","audio":"071/071_005_003.mp3"},{"id":"83557","char_type":"word","text":"دَعَوْتُ","aya":"5","sura":"71","audio":"071/071_005_004.mp3"},{"id":"83558","char_type":"word","text":"قَوْمِي","aya":"5","sura":"71","audio":"071/071_005_005.mp3"},{"id":"83559","char_type":"word","text":"لَيْلًا","aya":"5","sura":"71","audio":"071/071_005_006.mp3"},{"id":"83560","char_type":"word","text":"وَنَهَارًا","aya":"5","sura":"71","audio":"071/071_005_007.mp3"},{"id":"83561","char_type":"end","text":null,"aya":"5","sura":"71","audio":"071005.mp3"},{"id":"83562","char_type":"word","text":"فَلَمْ","aya":"6","sura":"71","audio":"071/071_006_001.mp3"},{"id":"83563","char_type":"word","text":"يَزِدْهُمْ","aya":"6","sura":"71","audio":"071/071_006_002.mp3"},{"id":"83564","char_type":"word","text":"دُعَائِي","aya":"6","sura":"71","audio":"071/071_006_003.mp3"},{"id":"83565","char_type":"word","text":"إِلَّا","aya":"6","sura":"71","audio":"071/071_006_004.mp3"}],"lineId":8532},{"line":12,"type":"line","surahNumber":"71","surah":"نوح","index":null,"ayah":"6","text":[{"id":"83566","char_type":"word","text":"فِرَارًا","aya":"6","sura":"71","audio":"071/071_006_005.mp3"},{"id":"83567","char_type":"end","text":null,"aya":"6","sura":"71","audio":"071006.mp3"},{"id":"83568","char_type":"word","text":"وَإِنِّي","aya":"7","sura":"71","audio":"071/071_007_001.mp3"},{"id":"83569","char_type":"word","text":"كُلَّمَا","aya":"7","sura":"71","audio":"071/071_007_002.mp3"},{"id":"83570","char_type":"word","text":"دَعَوْتُهُمْ","aya":"7","sura":"71","audio":"071/071_007_003.mp3"},{"id":"83571","char_type":"word","text":"لِتَغْفِرَ","aya":"7","sura":"71","audio":"071/071_007_004.mp3"},{"id":"83572","char_type":"word","text":"لَهُمْ","aya":"7","sura":"71","audio":"071/071_007_005.mp3"},{"id":"83573","char_type":"word","text":"جَعَلُوا","aya":"7","sura":"71","audio":"071/071_007_006.mp3"},{"id":"83574","char_type":"word","text":"أَصَابِعَهُمْ","aya":"7","sura":"71","audio":"071/071_007_007.mp3"}],"lineId":8533},{"line":13,"type":"line","surahNumber":"71","surah":"نوح","index":null,"ayah":"7","text":[{"id":"83575","char_type":"word","text":"فِي","aya":"7","sura":"71","audio":"071/071_007_008.mp3"},{"id":"83576","char_type":"word","text":"آذَانِهِمْ","aya":"7","sura":"71","audio":"071/071_007_009.mp3"},{"id":"83577","char_type":"word","text":"وَاسْتَغْشَوْا","aya":"7","sura":"71","audio":"071/071_007_010.mp3"},{"id":"83578","char_type":"word","text":"ثِيَابَهُمْ","aya":"7","sura":"71","audio":"071/071_007_011.mp3"},{"id":"83579","char_type":"word","text":"وَأَصَرُّوا","aya":"7","sura":"71","audio":"071/071_007_012.mp3"},{"id":"83580","char_type":"word","text":"وَاسْتَكْبَرُوا","aya":"7","sura":"71","audio":"071/071_007_013.mp3"},{"id":"83581","char_type":"word","text":"اسْتِكْبَارًا","aya":"7","sura":"71","audio":"071/071_007_014.mp3"}],"lineId":8534},{"line":14,"type":"line","surahNumber":"71","surah":"نوح","index":null,"ayah":"7","text":[{"id":"83582","char_type":"end","text":null,"aya":"7","sura":"71","audio":"071007.mp3"},{"id":"83583","char_type":"word","text":"ثُمَّ","aya":"8","sura":"71","audio":"071/071_008_001.mp3"},{"id":"83584","char_type":"word","text":"إِنِّي","aya":"8","sura":"71","audio":"071/071_008_002.mp3"},{"id":"83585","char_type":"word","text":"دَعَوْتُهُمْ","aya":"8","sura":"71","audio":"071/071_008_003.mp3"},{"id":"83586","char_type":"word","text":"جِهَارًا","aya":"8","sura":"71","audio":"071/071_008_004.mp3"},{"id":"83587","char_type":"end","text":null,"aya":"8","sura":"71","audio":"071008.mp3"},{"id":"83588","char_type":"word","text":"ثُمَّ","aya":"9","sura":"71","audio":"071/071_009_001.mp3"},{"id":"83589","char_type":"word","text":"إِنِّي","aya":"9","sura":"71","audio":"071/071_009_002.mp3"},{"id":"83590","char_type":"word","text":"أَعْلَنْتُ","aya":"9","sura":"71","audio":"071/071_009_003.mp3"},{"id":"83591","char_type":"word","text":"لَهُمْ","aya":"9","sura":"71","audio":"071/071_009_004.mp3"},{"id":"83592","char_type":"word","text":"وَأَسْرَرْتُ","aya":"9","sura":"71","audio":"071/071_009_005.mp3"}],"lineId":8535},{"line":15,"type":"line","surahNumber":"71","surah":"نوح","index":null,"ayah":"9","text":[{"id":"83593","char_type":"word","text":"لَهُمْ","aya":"9","sura":"71","audio":"071/071_009_006.mp3"},{"id":"83594","char_type":"word","text":"إِسْرَارًا","aya":"9","sura":"71","audio":"071/071_009_007.mp3"},{"id":"83595","char_type":"end","text":null,"aya":"9","sura":"71","audio":"071009.mp3"},{"id":"83596","char_type":"word","text":"فَقُلْتُ","aya":"10","sura":"71","audio":"071/071_010_001.mp3"},{"id":"83597","char_type":"word","text":"اسْتَغْفِرُوا","aya":"10","sura":"71","audio":"071/071_010_002.mp3"},{"id":"83598","char_type":"word","text":"رَبَّكُمْ","aya":"10","sura":"71","audio":"071/071_010_003.mp3"},{"id":"83599","char_type":"word","text":"إِنَّهُ","aya":"10","sura":"71","audio":"071/071_010_004.mp3"},{"id":"83600","char_type":"word","text":"كَانَ","aya":"10","sura":"71","audio":"071/071_010_005.mp3"},{"id":"83601","char_type":"word","text":"غَفَّارًا","aya":"10","sura":"71","audio":"071/071_010_006.mp3"},{"id":"83602","char_type":"end","text":null,"aya":"10","sura":"71","audio":"071010.mp3"}],"lineId":8536}]