[{"line":1,"type":"line","surahNumber":"3","surah":"آل عمران","index":null,"ayah":"141","text":[{"id":"9523","char_type":"word","text":"وَلِيُمَحِّصَ","aya":"141","sura":"3","audio":"003/003_141_001.mp3"},{"id":"9524","char_type":"word","text":"اللَّهُ","aya":"141","sura":"3","audio":"003/003_141_002.mp3"},{"id":"9525","char_type":"word","text":"الَّذِينَ","aya":"141","sura":"3","audio":"003/003_141_003.mp3"},{"id":"9526","char_type":"word","text":"آمَنُوا","aya":"141","sura":"3","audio":"003/003_141_004.mp3"},{"id":"9527","char_type":"word","text":"وَيَمْحَقَ","aya":"141","sura":"3","audio":"003/003_141_005.mp3"},{"id":"9528","char_type":"word","text":"الْكَافِرِينَ","aya":"141","sura":"3","audio":"003/003_141_006.mp3"},{"id":"9529","char_type":"end","text":null,"aya":"141","sura":"3","audio":"003141.mp3"},{"id":"9530","char_type":"word","text":"أَمْ","aya":"142","sura":"3","audio":"003/003_142_001.mp3"}],"lineId":992},{"line":2,"type":"line","surahNumber":"3","surah":"آل عمران","index":null,"ayah":"142","text":[{"id":"9531","char_type":"word","text":"حَسِبْتُمْ","aya":"142","sura":"3","audio":"003/003_142_002.mp3"},{"id":"9532","char_type":"word","text":"أَنْ","aya":"142","sura":"3","audio":"003/003_142_003.mp3"},{"id":"9533","char_type":"word","text":"تَدْخُلُوا","aya":"142","sura":"3","audio":"003/003_142_004.mp3"},{"id":"9534","char_type":"word","text":"الْجَنَّةَ","aya":"142","sura":"3","audio":"003/003_142_005.mp3"},{"id":"9535","char_type":"word","text":"وَلَمَّا","aya":"142","sura":"3","audio":"003/003_142_006.mp3"},{"id":"9536","char_type":"word","text":"يَعْلَمِ","aya":"142","sura":"3","audio":"003/003_142_007.mp3"},{"id":"9537","char_type":"word","text":"اللَّهُ","aya":"142","sura":"3","audio":"003/003_142_008.mp3"},{"id":"9538","char_type":"word","text":"الَّذِينَ","aya":"142","sura":"3","audio":"003/003_142_009.mp3"},{"id":"9539","char_type":"word","text":"جَاهَدُوا","aya":"142","sura":"3","audio":"003/003_142_010.mp3"}],"lineId":993},{"line":3,"type":"line","surahNumber":"3","surah":"آل عمران","index":null,"ayah":"142","text":[{"id":"9540","char_type":"word","text":"مِنْكُمْ","aya":"142","sura":"3","audio":"003/003_142_011.mp3"},{"id":"9541","char_type":"word","text":"وَيَعْلَمَ","aya":"142","sura":"3","audio":"003/003_142_012.mp3"},{"id":"9542","char_type":"word","text":"الصَّابِرِينَ","aya":"142","sura":"3","audio":"003/003_142_013.mp3"},{"id":"9543","char_type":"end","text":null,"aya":"142","sura":"3","audio":"003142.mp3"},{"id":"9544","char_type":"word","text":"وَلَقَدْ","aya":"143","sura":"3","audio":"003/003_143_001.mp3"},{"id":"9545","char_type":"word","text":"كُنْتُمْ","aya":"143","sura":"3","audio":"003/003_143_002.mp3"},{"id":"9546","char_type":"word","text":"تَمَنَّوْنَ","aya":"143","sura":"3","audio":"003/003_143_003.mp3"},{"id":"9547","char_type":"word","text":"الْمَوْتَ","aya":"143","sura":"3","audio":"003/003_143_004.mp3"},{"id":"9548","char_type":"word","text":"مِنْ","aya":"143","sura":"3","audio":"003/003_143_005.mp3"}],"lineId":994},{"line":4,"type":"line","surahNumber":"3","surah":"آل عمران","index":null,"ayah":"143","text":[{"id":"9549","char_type":"word","text":"قَبْلِ","aya":"143","sura":"3","audio":"003/003_143_006.mp3"},{"id":"9550","char_type":"word","text":"أَنْ","aya":"143","sura":"3","audio":"003/003_143_007.mp3"},{"id":"9551","char_type":"word","text":"تَلْقَوْهُ","aya":"143","sura":"3","audio":"003/003_143_008.mp3"},{"id":"9552","char_type":"word","text":"فَقَدْ","aya":"143","sura":"3","audio":"003/003_143_009.mp3"},{"id":"9553","char_type":"word","text":"رَأَيْتُمُوهُ","aya":"143","sura":"3","audio":"003/003_143_010.mp3"},{"id":"9554","char_type":"word","text":"وَأَنْتُمْ","aya":"143","sura":"3","audio":"003/003_143_011.mp3"},{"id":"9555","char_type":"word","text":"تَنْظُرُونَ","aya":"143","sura":"3","audio":"003/003_143_012.mp3"},{"id":"9556","char_type":"end","text":null,"aya":"143","sura":"3","audio":"003143.mp3"},{"id":"9557","char_type":"word","text":"وَمَا","aya":"144","sura":"3","audio":"003/003_144_001.mp3"},{"id":"9558","char_type":"word","text":"مُحَمَّدٌ","aya":"144","sura":"3","audio":"003/003_144_002.mp3"}],"lineId":995},{"line":5,"type":"line","surahNumber":"3","surah":"آل عمران","index":null,"ayah":"144","text":[{"id":"9559","char_type":"word","text":"إِلَّا","aya":"144","sura":"3","audio":"003/003_144_003.mp3"},{"id":"9560","char_type":"word","text":"رَسُولٌ","aya":"144","sura":"3","audio":"003/003_144_004.mp3"},{"id":"9561","char_type":"word","text":"قَدْ","aya":"144","sura":"3","audio":"003/003_144_005.mp3"},{"id":"9562","char_type":"word","text":"خَلَتْ","aya":"144","sura":"3","audio":"003/003_144_006.mp3"},{"id":"9563","char_type":"word","text":"مِنْ","aya":"144","sura":"3","audio":"003/003_144_007.mp3"},{"id":"9564","char_type":"word","text":"قَبْلِهِ","aya":"144","sura":"3","audio":"003/003_144_008.mp3"},{"id":"9565","char_type":"word","text":"الرُّسُلُ","aya":"144","sura":"3","audio":"003/003_144_009.mp3"},{"id":"9566","char_type":"pause","text":"ۚ","aya":"144","sura":"3","audio":null},{"id":"9567","char_type":"word","text":"أَفَإِنْ","aya":"144","sura":"3","audio":"003/003_144_011.mp3"},{"id":"9568","char_type":"word","text":"مَاتَ","aya":"144","sura":"3","audio":"003/003_144_012.mp3"},{"id":"9569","char_type":"word","text":"أَوْ","aya":"144","sura":"3","audio":"003/003_144_013.mp3"},{"id":"9570","char_type":"word","text":"قُتِلَ","aya":"144","sura":"3","audio":"003/003_144_014.mp3"}],"lineId":996},{"line":6,"type":"line","surahNumber":"3","surah":"آل عمران","index":null,"ayah":"144","text":[{"id":"9571","char_type":"word","text":"انْقَلَبْتُمْ","aya":"144","sura":"3","audio":"003/003_144_015.mp3"},{"id":"9572","char_type":"word","text":"عَلَىٰ","aya":"144","sura":"3","audio":"003/003_144_016.mp3"},{"id":"9573","char_type":"word","text":"أَعْقَابِكُمْ","aya":"144","sura":"3","audio":"003/003_144_017.mp3"},{"id":"9574","char_type":"pause","text":"ۚ","aya":"144","sura":"3","audio":null},{"id":"9575","char_type":"word","text":"وَمَنْ","aya":"144","sura":"3","audio":"003/003_144_019.mp3"},{"id":"9576","char_type":"word","text":"يَنْقَلِبْ","aya":"144","sura":"3","audio":"003/003_144_020.mp3"},{"id":"9577","char_type":"word","text":"عَلَىٰ","aya":"144","sura":"3","audio":"003/003_144_021.mp3"},{"id":"9578","char_type":"word","text":"عَقِبَيْهِ","aya":"144","sura":"3","audio":"003/003_144_022.mp3"},{"id":"9579","char_type":"word","text":"فَلَنْ","aya":"144","sura":"3","audio":"003/003_144_023.mp3"},{"id":"9580","char_type":"word","text":"يَضُرَّ","aya":"144","sura":"3","audio":"003/003_144_024.mp3"}],"lineId":997},{"line":7,"type":"line","surahNumber":"3","surah":"آل عمران","index":null,"ayah":"144","text":[{"id":"9581","char_type":"word","text":"اللَّهَ","aya":"144","sura":"3","audio":"003/003_144_025.mp3"},{"id":"9582","char_type":"word","text":"شَيْئًا","aya":"144","sura":"3","audio":"003/003_144_026.mp3"},{"id":"9583","char_type":"pause","text":"ۗ","aya":"144","sura":"3","audio":null},{"id":"9584","char_type":"word","text":"وَسَيَجْزِي","aya":"144","sura":"3","audio":"003/003_144_028.mp3"},{"id":"9585","char_type":"word","text":"اللَّهُ","aya":"144","sura":"3","audio":"003/003_144_029.mp3"},{"id":"9586","char_type":"word","text":"الشَّاكِرِينَ","aya":"144","sura":"3","audio":"003/003_144_030.mp3"},{"id":"9587","char_type":"end","text":null,"aya":"144","sura":"3","audio":"003144.mp3"},{"id":"9588","char_type":"word","text":"وَمَا","aya":"145","sura":"3","audio":"003/003_145_001.mp3"},{"id":"9589","char_type":"word","text":"كَانَ","aya":"145","sura":"3","audio":"003/003_145_002.mp3"}],"lineId":998},{"line":8,"type":"line","surahNumber":"3","surah":"آل عمران","index":null,"ayah":"145","text":[{"id":"9590","char_type":"word","text":"لِنَفْسٍ","aya":"145","sura":"3","audio":"003/003_145_003.mp3"},{"id":"9591","char_type":"word","text":"أَنْ","aya":"145","sura":"3","audio":"003/003_145_004.mp3"},{"id":"9592","char_type":"word","text":"تَمُوتَ","aya":"145","sura":"3","audio":"003/003_145_005.mp3"},{"id":"9593","char_type":"word","text":"إِلَّا","aya":"145","sura":"3","audio":"003/003_145_006.mp3"},{"id":"9594","char_type":"word","text":"بِإِذْنِ","aya":"145","sura":"3","audio":"003/003_145_007.mp3"},{"id":"9595","char_type":"word","text":"اللَّهِ","aya":"145","sura":"3","audio":"003/003_145_008.mp3"},{"id":"9596","char_type":"word","text":"كِتَابًا","aya":"145","sura":"3","audio":"003/003_145_009.mp3"},{"id":"9597","char_type":"word","text":"مُؤَجَّلًا","aya":"145","sura":"3","audio":"003/003_145_010.mp3"},{"id":"9598","char_type":"pause","text":"ۗ","aya":"145","sura":"3","audio":null},{"id":"9599","char_type":"word","text":"وَمَنْ","aya":"145","sura":"3","audio":"003/003_145_012.mp3"},{"id":"9600","char_type":"word","text":"يُرِدْ","aya":"145","sura":"3","audio":"003/003_145_013.mp3"}],"lineId":999},{"line":9,"type":"line","surahNumber":"3","surah":"آل عمران","index":null,"ayah":"145","text":[{"id":"9601","char_type":"word","text":"ثَوَابَ","aya":"145","sura":"3","audio":"003/003_145_014.mp3"},{"id":"9602","char_type":"word","text":"الدُّنْيَا","aya":"145","sura":"3","audio":"003/003_145_015.mp3"},{"id":"9603","char_type":"word","text":"نُؤْتِهِ","aya":"145","sura":"3","audio":"003/003_145_016.mp3"},{"id":"9604","char_type":"word","text":"مِنْهَا","aya":"145","sura":"3","audio":"003/003_145_017.mp3"},{"id":"9605","char_type":"word","text":"وَمَنْ","aya":"145","sura":"3","audio":"003/003_145_018.mp3"},{"id":"9606","char_type":"word","text":"يُرِدْ","aya":"145","sura":"3","audio":"003/003_145_019.mp3"},{"id":"9607","char_type":"word","text":"ثَوَابَ","aya":"145","sura":"3","audio":"003/003_145_020.mp3"},{"id":"9608","char_type":"word","text":"الْآخِرَةِ","aya":"145","sura":"3","audio":"003/003_145_021.mp3"},{"id":"9609","char_type":"word","text":"نُؤْتِهِ","aya":"145","sura":"3","audio":"003/003_145_022.mp3"}],"lineId":1000},{"line":10,"type":"line","surahNumber":"3","surah":"آل عمران","index":null,"ayah":"145","text":[{"id":"9610","char_type":"word","text":"مِنْهَا","aya":"145","sura":"3","audio":"003/003_145_023.mp3"},{"id":"9611","char_type":"pause","text":"ۚ","aya":"145","sura":"3","audio":null},{"id":"9612","char_type":"word","text":"وَسَنَجْزِي","aya":"145","sura":"3","audio":"003/003_145_025.mp3"},{"id":"9613","char_type":"word","text":"الشَّاكِرِينَ","aya":"145","sura":"3","audio":"003/003_145_026.mp3"},{"id":"9614","char_type":"end","text":null,"aya":"145","sura":"3","audio":"003145.mp3"},{"id":"9615","char_type":"word","text":"وَكَأَيِّنْ","aya":"146","sura":"3","audio":"003/003_146_001.mp3"},{"id":"9616","char_type":"word","text":"مِنْ","aya":"146","sura":"3","audio":"003/003_146_002.mp3"},{"id":"9617","char_type":"word","text":"نَبِيٍّ","aya":"146","sura":"3","audio":"003/003_146_003.mp3"},{"id":"9618","char_type":"word","text":"قَاتَلَ","aya":"146","sura":"3","audio":"003/003_146_004.mp3"},{"id":"9619","char_type":"word","text":"مَعَهُ","aya":"146","sura":"3","audio":"003/003_146_005.mp3"}],"lineId":1001},{"line":11,"type":"line","surahNumber":"3","surah":"آل عمران","index":null,"ayah":"146","text":[{"id":"9620","char_type":"word","text":"رِبِّيُّونَ","aya":"146","sura":"3","audio":"003/003_146_006.mp3"},{"id":"9621","char_type":"word","text":"كَثِيرٌ","aya":"146","sura":"3","audio":"003/003_146_007.mp3"},{"id":"9622","char_type":"word","text":"فَمَا","aya":"146","sura":"3","audio":"003/003_146_008.mp3"},{"id":"9623","char_type":"word","text":"وَهَنُوا","aya":"146","sura":"3","audio":"003/003_146_009.mp3"},{"id":"9624","char_type":"word","text":"لِمَا","aya":"146","sura":"3","audio":"003/003_146_010.mp3"},{"id":"9625","char_type":"word","text":"أَصَابَهُمْ","aya":"146","sura":"3","audio":"003/003_146_011.mp3"},{"id":"9626","char_type":"word","text":"فِي","aya":"146","sura":"3","audio":"003/003_146_012.mp3"},{"id":"9627","char_type":"word","text":"سَبِيلِ","aya":"146","sura":"3","audio":"003/003_146_013.mp3"},{"id":"9628","char_type":"word","text":"اللَّهِ","aya":"146","sura":"3","audio":"003/003_146_014.mp3"},{"id":"9629","char_type":"word","text":"وَمَا","aya":"146","sura":"3","audio":"003/003_146_015.mp3"},{"id":"9630","char_type":"word","text":"ضَعُفُوا","aya":"146","sura":"3","audio":"003/003_146_016.mp3"}],"lineId":1002},{"line":12,"type":"line","surahNumber":"3","surah":"آل عمران","index":null,"ayah":"146","text":[{"id":"9631","char_type":"word","text":"وَمَا","aya":"146","sura":"3","audio":"003/003_146_017.mp3"},{"id":"9632","char_type":"word","text":"اسْتَكَانُوا","aya":"146","sura":"3","audio":"003/003_146_018.mp3"},{"id":"9633","char_type":"pause","text":"ۗ","aya":"146","sura":"3","audio":null},{"id":"9634","char_type":"word","text":"وَاللَّهُ","aya":"146","sura":"3","audio":"003/003_146_020.mp3"},{"id":"9635","char_type":"word","text":"يُحِبُّ","aya":"146","sura":"3","audio":"003/003_146_021.mp3"},{"id":"9636","char_type":"word","text":"الصَّابِرِينَ","aya":"146","sura":"3","audio":"003/003_146_022.mp3"},{"id":"9637","char_type":"end","text":null,"aya":"146","sura":"3","audio":"003146.mp3"},{"id":"9638","char_type":"word","text":"وَمَا","aya":"147","sura":"3","audio":"003/003_147_001.mp3"},{"id":"9639","char_type":"word","text":"كَانَ","aya":"147","sura":"3","audio":"003/003_147_002.mp3"},{"id":"9640","char_type":"word","text":"قَوْلَهُمْ","aya":"147","sura":"3","audio":"003/003_147_003.mp3"}],"lineId":1003},{"line":13,"type":"line","surahNumber":"3","surah":"آل عمران","index":null,"ayah":"147","text":[{"id":"9641","char_type":"word","text":"إِلَّا","aya":"147","sura":"3","audio":"003/003_147_004.mp3"},{"id":"9642","char_type":"word","text":"أَنْ","aya":"147","sura":"3","audio":"003/003_147_005.mp3"},{"id":"9643","char_type":"word","text":"قَالُوا","aya":"147","sura":"3","audio":"003/003_147_006.mp3"},{"id":"9644","char_type":"word","text":"رَبَّنَا","aya":"147","sura":"3","audio":"003/003_147_007.mp3"},{"id":"9645","char_type":"word","text":"اغْفِرْ","aya":"147","sura":"3","audio":"003/003_147_008.mp3"},{"id":"9646","char_type":"word","text":"لَنَا","aya":"147","sura":"3","audio":"003/003_147_009.mp3"},{"id":"9647","char_type":"word","text":"ذُنُوبَنَا","aya":"147","sura":"3","audio":"003/003_147_010.mp3"},{"id":"9648","char_type":"word","text":"وَإِسْرَافَنَا","aya":"147","sura":"3","audio":"003/003_147_011.mp3"},{"id":"9649","char_type":"word","text":"فِي","aya":"147","sura":"3","audio":"003/003_147_012.mp3"},{"id":"9650","char_type":"word","text":"أَمْرِنَا","aya":"147","sura":"3","audio":"003/003_147_013.mp3"},{"id":"9651","char_type":"word","text":"وَثَبِّتْ","aya":"147","sura":"3","audio":"003/003_147_014.mp3"}],"lineId":1004},{"line":14,"type":"line","surahNumber":"3","surah":"آل عمران","index":null,"ayah":"147","text":[{"id":"9652","char_type":"word","text":"أَقْدَامَنَا","aya":"147","sura":"3","audio":"003/003_147_015.mp3"},{"id":"9653","char_type":"word","text":"وَانْصُرْنَا","aya":"147","sura":"3","audio":"003/003_147_016.mp3"},{"id":"9654","char_type":"word","text":"عَلَى","aya":"147","sura":"3","audio":"003/003_147_017.mp3"},{"id":"9655","char_type":"word","text":"الْقَوْمِ","aya":"147","sura":"3","audio":"003/003_147_018.mp3"},{"id":"9656","char_type":"word","text":"الْكَافِرِينَ","aya":"147","sura":"3","audio":"003/003_147_019.mp3"},{"id":"9657","char_type":"end","text":null,"aya":"147","sura":"3","audio":"003147.mp3"},{"id":"9658","char_type":"word","text":"فَآتَاهُمُ","aya":"148","sura":"3","audio":"003/003_148_001.mp3"},{"id":"9659","char_type":"word","text":"اللَّهُ","aya":"148","sura":"3","audio":"003/003_148_002.mp3"}],"lineId":1005},{"line":15,"type":"line","surahNumber":"3","surah":"آل عمران","index":null,"ayah":"148","text":[{"id":"9660","char_type":"word","text":"ثَوَابَ","aya":"148","sura":"3","audio":"003/003_148_003.mp3"},{"id":"9661","char_type":"word","text":"الدُّنْيَا","aya":"148","sura":"3","audio":"003/003_148_004.mp3"},{"id":"9662","char_type":"word","text":"وَحُسْنَ","aya":"148","sura":"3","audio":"003/003_148_005.mp3"},{"id":"9663","char_type":"word","text":"ثَوَابِ","aya":"148","sura":"3","audio":"003/003_148_006.mp3"},{"id":"9664","char_type":"word","text":"الْآخِرَةِ","aya":"148","sura":"3","audio":"003/003_148_007.mp3"},{"id":"9665","char_type":"pause","text":"ۗ","aya":"148","sura":"3","audio":null},{"id":"9666","char_type":"word","text":"وَاللَّهُ","aya":"148","sura":"3","audio":"003/003_148_009.mp3"},{"id":"9667","char_type":"word","text":"يُحِبُّ","aya":"148","sura":"3","audio":"003/003_148_010.mp3"},{"id":"9668","char_type":"word","text":"الْمُحْسِنِينَ","aya":"148","sura":"3","audio":"003/003_148_011.mp3"},{"id":"9669","char_type":"end","text":null,"aya":"148","sura":"3","audio":"003148.mp3"}],"lineId":1006}]