[{"line":1,"type":"line","surahNumber":"4","surah":"النساء","index":null,"ayah":"95","text":[{"id":"13219","char_type":"word","text":"لَا","aya":"95","sura":"4","audio":"004/004_095_001.mp3"},{"id":"13220","char_type":"word","text":"يَسْتَوِي","aya":"95","sura":"4","audio":"004/004_095_002.mp3"},{"id":"13221","char_type":"word","text":"الْقَاعِدُونَ","aya":"95","sura":"4","audio":"004/004_095_003.mp3"},{"id":"13222","char_type":"word","text":"مِنَ","aya":"95","sura":"4","audio":"004/004_095_004.mp3"},{"id":"13223","char_type":"word","text":"الْمُؤْمِنِينَ","aya":"95","sura":"4","audio":"004/004_095_005.mp3"},{"id":"13224","char_type":"word","text":"غَيْرُ","aya":"95","sura":"4","audio":"004/004_095_006.mp3"},{"id":"13225","char_type":"word","text":"أُولِي","aya":"95","sura":"4","audio":"004/004_095_007.mp3"},{"id":"13226","char_type":"word","text":"الضَّرَرِ","aya":"95","sura":"4","audio":"004/004_095_008.mp3"},{"id":"13227","char_type":"word","text":"وَالْمُجَاهِدُونَ","aya":"95","sura":"4","audio":"004/004_095_009.mp3"}],"lineId":1382},{"line":2,"type":"line","surahNumber":"4","surah":"النساء","index":null,"ayah":"95","text":[{"id":"13228","char_type":"word","text":"فِي","aya":"95","sura":"4","audio":"004/004_095_010.mp3"},{"id":"13229","char_type":"word","text":"سَبِيلِ","aya":"95","sura":"4","audio":"004/004_095_011.mp3"},{"id":"13230","char_type":"word","text":"اللَّهِ","aya":"95","sura":"4","audio":"004/004_095_012.mp3"},{"id":"13231","char_type":"word","text":"بِأَمْوَالِهِمْ","aya":"95","sura":"4","audio":"004/004_095_013.mp3"},{"id":"13232","char_type":"word","text":"وَأَنْفُسِهِمْ","aya":"95","sura":"4","audio":"004/004_095_014.mp3"},{"id":"13233","char_type":"pause","text":"ۚ","aya":"95","sura":"4","audio":null},{"id":"13234","char_type":"word","text":"فَضَّلَ","aya":"95","sura":"4","audio":"004/004_095_016.mp3"},{"id":"13235","char_type":"word","text":"اللَّهُ","aya":"95","sura":"4","audio":"004/004_095_017.mp3"},{"id":"13236","char_type":"word","text":"الْمُجَاهِدِينَ","aya":"95","sura":"4","audio":"004/004_095_018.mp3"},{"id":"13237","char_type":"word","text":"بِأَمْوَالِهِمْ","aya":"95","sura":"4","audio":"004/004_095_019.mp3"}],"lineId":1383},{"line":3,"type":"line","surahNumber":"4","surah":"النساء","index":null,"ayah":"95","text":[{"id":"13238","char_type":"word","text":"وَأَنْفُسِهِمْ","aya":"95","sura":"4","audio":"004/004_095_020.mp3"},{"id":"13239","char_type":"word","text":"عَلَى","aya":"95","sura":"4","audio":"004/004_095_021.mp3"},{"id":"13240","char_type":"word","text":"الْقَاعِدِينَ","aya":"95","sura":"4","audio":"004/004_095_022.mp3"},{"id":"13241","char_type":"word","text":"دَرَجَةً","aya":"95","sura":"4","audio":"004/004_095_023.mp3"},{"id":"13242","char_type":"pause","text":"ۚ","aya":"95","sura":"4","audio":null},{"id":"13243","char_type":"word","text":"وَكُلًّا","aya":"95","sura":"4","audio":"004/004_095_025.mp3"},{"id":"13244","char_type":"word","text":"وَعَدَ","aya":"95","sura":"4","audio":"004/004_095_026.mp3"},{"id":"13245","char_type":"word","text":"اللَّهُ","aya":"95","sura":"4","audio":"004/004_095_027.mp3"},{"id":"13246","char_type":"word","text":"الْحُسْنَىٰ","aya":"95","sura":"4","audio":"004/004_095_028.mp3"},{"id":"13247","char_type":"pause","text":"ۚ","aya":"95","sura":"4","audio":null},{"id":"13248","char_type":"word","text":"وَفَضَّلَ","aya":"95","sura":"4","audio":"004/004_095_030.mp3"},{"id":"13249","char_type":"word","text":"اللَّهُ","aya":"95","sura":"4","audio":"004/004_095_031.mp3"}],"lineId":1384},{"line":4,"type":"line","surahNumber":"4","surah":"النساء","index":null,"ayah":"95","text":[{"id":"13250","char_type":"word","text":"الْمُجَاهِدِينَ","aya":"95","sura":"4","audio":"004/004_095_032.mp3"},{"id":"13251","char_type":"word","text":"عَلَى","aya":"95","sura":"4","audio":"004/004_095_033.mp3"},{"id":"13252","char_type":"word","text":"الْقَاعِدِينَ","aya":"95","sura":"4","audio":"004/004_095_034.mp3"},{"id":"13253","char_type":"word","text":"أَجْرًا","aya":"95","sura":"4","audio":"004/004_095_035.mp3"},{"id":"13254","char_type":"word","text":"عَظِيمًا","aya":"95","sura":"4","audio":"004/004_095_036.mp3"},{"id":"13255","char_type":"end","text":null,"aya":"95","sura":"4","audio":"004095.mp3"},{"id":"13256","char_type":"word","text":"دَرَجَاتٍ","aya":"96","sura":"4","audio":"004/004_096_001.mp3"},{"id":"13257","char_type":"word","text":"مِنْهُ","aya":"96","sura":"4","audio":"004/004_096_002.mp3"},{"id":"13258","char_type":"word","text":"وَمَغْفِرَةً","aya":"96","sura":"4","audio":"004/004_096_003.mp3"}],"lineId":1385},{"line":5,"type":"line","surahNumber":"4","surah":"النساء","index":null,"ayah":"96","text":[{"id":"13259","char_type":"word","text":"وَرَحْمَةً","aya":"96","sura":"4","audio":"004/004_096_004.mp3"},{"id":"13260","char_type":"pause","text":"ۚ","aya":"96","sura":"4","audio":null},{"id":"13261","char_type":"word","text":"وَكَانَ","aya":"96","sura":"4","audio":"004/004_096_006.mp3"},{"id":"13262","char_type":"word","text":"اللَّهُ","aya":"96","sura":"4","audio":"004/004_096_007.mp3"},{"id":"13263","char_type":"word","text":"غَفُورًا","aya":"96","sura":"4","audio":"004/004_096_008.mp3"},{"id":"13264","char_type":"word","text":"رَحِيمًا","aya":"96","sura":"4","audio":"004/004_096_009.mp3"},{"id":"13265","char_type":"end","text":null,"aya":"96","sura":"4","audio":"004096.mp3"},{"id":"13266","char_type":"word","text":"إِنَّ","aya":"97","sura":"4","audio":"004/004_097_001.mp3"},{"id":"13267","char_type":"word","text":"الَّذِينَ","aya":"97","sura":"4","audio":"004/004_097_002.mp3"},{"id":"13268","char_type":"word","text":"تَوَفَّاهُمُ","aya":"97","sura":"4","audio":"004/004_097_003.mp3"},{"id":"13269","char_type":"word","text":"الْمَلَائِكَةُ","aya":"97","sura":"4","audio":"004/004_097_004.mp3"}],"lineId":1386},{"line":6,"type":"line","surahNumber":"4","surah":"النساء","index":null,"ayah":"97","text":[{"id":"13270","char_type":"word","text":"ظَالِمِي","aya":"97","sura":"4","audio":"004/004_097_005.mp3"},{"id":"13271","char_type":"word","text":"أَنْفُسِهِمْ","aya":"97","sura":"4","audio":"004/004_097_006.mp3"},{"id":"13272","char_type":"word","text":"قَالُوا","aya":"97","sura":"4","audio":"004/004_097_007.mp3"},{"id":"13273","char_type":"word","text":"فِيمَ","aya":"97","sura":"4","audio":"004/004_097_008.mp3"},{"id":"13274","char_type":"word","text":"كُنْتُمْ","aya":"97","sura":"4","audio":"004/004_097_009.mp3"},{"id":"13275","char_type":"pause","text":"ۖ","aya":"97","sura":"4","audio":null},{"id":"13276","char_type":"word","text":"قَالُوا","aya":"97","sura":"4","audio":"004/004_097_011.mp3"},{"id":"13277","char_type":"word","text":"كُنَّا","aya":"97","sura":"4","audio":"004/004_097_012.mp3"},{"id":"13278","char_type":"word","text":"مُسْتَضْعَفِينَ","aya":"97","sura":"4","audio":"004/004_097_013.mp3"},{"id":"13279","char_type":"word","text":"فِي","aya":"97","sura":"4","audio":"004/004_097_014.mp3"},{"id":"13280","char_type":"word","text":"الْأَرْضِ","aya":"97","sura":"4","audio":"004/004_097_015.mp3"},{"id":"13281","char_type":"pause","text":"ۚ","aya":"97","sura":"4","audio":null}],"lineId":1387},{"line":7,"type":"line","surahNumber":"4","surah":"النساء","index":null,"ayah":"97","text":[{"id":"13282","char_type":"word","text":"قَالُوا","aya":"97","sura":"4","audio":"004/004_097_017.mp3"},{"id":"13283","char_type":"word","text":"أَلَمْ","aya":"97","sura":"4","audio":"004/004_097_018.mp3"},{"id":"13284","char_type":"word","text":"تَكُنْ","aya":"97","sura":"4","audio":"004/004_097_019.mp3"},{"id":"13285","char_type":"word","text":"أَرْضُ","aya":"97","sura":"4","audio":"004/004_097_020.mp3"},{"id":"13286","char_type":"word","text":"اللَّهِ","aya":"97","sura":"4","audio":"004/004_097_021.mp3"},{"id":"13287","char_type":"word","text":"وَاسِعَةً","aya":"97","sura":"4","audio":"004/004_097_022.mp3"},{"id":"13288","char_type":"word","text":"فَتُهَاجِرُوا","aya":"97","sura":"4","audio":"004/004_097_023.mp3"},{"id":"13289","char_type":"word","text":"فِيهَا","aya":"97","sura":"4","audio":"004/004_097_024.mp3"},{"id":"13290","char_type":"pause","text":"ۚ","aya":"97","sura":"4","audio":null},{"id":"13291","char_type":"word","text":"فَأُولَٰئِكَ","aya":"97","sura":"4","audio":"004/004_097_026.mp3"},{"id":"13292","char_type":"word","text":"مَأْوَاهُمْ","aya":"97","sura":"4","audio":"004/004_097_027.mp3"}],"lineId":1388},{"line":8,"type":"line","surahNumber":"4","surah":"النساء","index":null,"ayah":"97","text":[{"id":"13293","char_type":"word","text":"جَهَنَّمُ","aya":"97","sura":"4","audio":"004/004_097_028.mp3"},{"id":"13294","char_type":"pause","text":"ۖ","aya":"97","sura":"4","audio":null},{"id":"13295","char_type":"word","text":"وَسَاءَتْ","aya":"97","sura":"4","audio":"004/004_097_030.mp3"},{"id":"13296","char_type":"word","text":"مَصِيرًا","aya":"97","sura":"4","audio":"004/004_097_031.mp3"},{"id":"13297","char_type":"end","text":null,"aya":"97","sura":"4","audio":"004097.mp3"},{"id":"13298","char_type":"word","text":"إِلَّا","aya":"98","sura":"4","audio":"004/004_098_001.mp3"},{"id":"13299","char_type":"word","text":"الْمُسْتَضْعَفِينَ","aya":"98","sura":"4","audio":"004/004_098_002.mp3"},{"id":"13300","char_type":"word","text":"مِنَ","aya":"98","sura":"4","audio":"004/004_098_003.mp3"},{"id":"13301","char_type":"word","text":"الرِّجَالِ","aya":"98","sura":"4","audio":"004/004_098_004.mp3"}],"lineId":1389},{"line":9,"type":"line","surahNumber":"4","surah":"النساء","index":null,"ayah":"98","text":[{"id":"13302","char_type":"word","text":"وَالنِّسَاءِ","aya":"98","sura":"4","audio":"004/004_098_005.mp3"},{"id":"13303","char_type":"word","text":"وَالْوِلْدَانِ","aya":"98","sura":"4","audio":"004/004_098_006.mp3"},{"id":"13304","char_type":"word","text":"لَا","aya":"98","sura":"4","audio":"004/004_098_007.mp3"},{"id":"13305","char_type":"word","text":"يَسْتَطِيعُونَ","aya":"98","sura":"4","audio":"004/004_098_008.mp3"},{"id":"13306","char_type":"word","text":"حِيلَةً","aya":"98","sura":"4","audio":"004/004_098_009.mp3"},{"id":"13307","char_type":"word","text":"وَلَا","aya":"98","sura":"4","audio":"004/004_098_010.mp3"},{"id":"13308","char_type":"word","text":"يَهْتَدُونَ","aya":"98","sura":"4","audio":"004/004_098_011.mp3"},{"id":"13309","char_type":"word","text":"سَبِيلًا","aya":"98","sura":"4","audio":"004/004_098_012.mp3"},{"id":"13310","char_type":"end","text":null,"aya":"98","sura":"4","audio":"004098.mp3"}],"lineId":1390},{"line":10,"type":"line","surahNumber":"4","surah":"النساء","index":null,"ayah":"99","text":[{"id":"13311","char_type":"word","text":"فَأُولَٰئِكَ","aya":"99","sura":"4","audio":"004/004_099_001.mp3"},{"id":"13312","char_type":"word","text":"عَسَى","aya":"99","sura":"4","audio":"004/004_099_002.mp3"},{"id":"13313","char_type":"word","text":"اللَّهُ","aya":"99","sura":"4","audio":"004/004_099_003.mp3"},{"id":"13314","char_type":"word","text":"أَنْ","aya":"99","sura":"4","audio":"004/004_099_004.mp3"},{"id":"13315","char_type":"word","text":"يَعْفُوَ","aya":"99","sura":"4","audio":"004/004_099_005.mp3"},{"id":"13316","char_type":"word","text":"عَنْهُمْ","aya":"99","sura":"4","audio":"004/004_099_006.mp3"},{"id":"13317","char_type":"pause","text":"ۚ","aya":"99","sura":"4","audio":null},{"id":"13318","char_type":"word","text":"وَكَانَ","aya":"99","sura":"4","audio":"004/004_099_008.mp3"},{"id":"13319","char_type":"word","text":"اللَّهُ","aya":"99","sura":"4","audio":"004/004_099_009.mp3"},{"id":"13320","char_type":"word","text":"عَفُوًّا","aya":"99","sura":"4","audio":"004/004_099_010.mp3"},{"id":"13321","char_type":"word","text":"غَفُورًا","aya":"99","sura":"4","audio":"004/004_099_011.mp3"},{"id":"13322","char_type":"end","text":null,"aya":"99","sura":"4","audio":"004099.mp3"}],"lineId":1391},{"line":11,"type":"line","surahNumber":"4","surah":"النساء","index":null,"ayah":"100","text":[{"id":"13323","char_type":"rub-el-hizb","text":"۞","aya":"100","sura":"4","audio":null},{"id":"13324","char_type":"word","text":"وَمَنْ","aya":"100","sura":"4","audio":"004/004_100_002.mp3"},{"id":"13325","char_type":"word","text":"يُهَاجِرْ","aya":"100","sura":"4","audio":"004/004_100_003.mp3"},{"id":"13326","char_type":"word","text":"فِي","aya":"100","sura":"4","audio":"004/004_100_004.mp3"},{"id":"13327","char_type":"word","text":"سَبِيلِ","aya":"100","sura":"4","audio":"004/004_100_005.mp3"},{"id":"13328","char_type":"word","text":"اللَّهِ","aya":"100","sura":"4","audio":"004/004_100_006.mp3"},{"id":"13329","char_type":"word","text":"يَجِدْ","aya":"100","sura":"4","audio":"004/004_100_007.mp3"},{"id":"13330","char_type":"word","text":"فِي","aya":"100","sura":"4","audio":"004/004_100_008.mp3"},{"id":"13331","char_type":"word","text":"الْأَرْضِ","aya":"100","sura":"4","audio":"004/004_100_009.mp3"},{"id":"13332","char_type":"word","text":"مُرَاغَمًا","aya":"100","sura":"4","audio":"004/004_100_010.mp3"},{"id":"13333","char_type":"word","text":"كَثِيرًا","aya":"100","sura":"4","audio":"004/004_100_011.mp3"},{"id":"13334","char_type":"word","text":"وَسَعَةً","aya":"100","sura":"4","audio":"004/004_100_012.mp3"},{"id":"13335","char_type":"pause","text":"ۚ","aya":"100","sura":"4","audio":null}],"lineId":1392},{"line":12,"type":"line","surahNumber":"4","surah":"النساء","index":null,"ayah":"100","text":[{"id":"13336","char_type":"word","text":"وَمَنْ","aya":"100","sura":"4","audio":"004/004_100_014.mp3"},{"id":"13337","char_type":"word","text":"يَخْرُجْ","aya":"100","sura":"4","audio":"004/004_100_015.mp3"},{"id":"13338","char_type":"word","text":"مِنْ","aya":"100","sura":"4","audio":"004/004_100_016.mp3"},{"id":"13339","char_type":"word","text":"بَيْتِهِ","aya":"100","sura":"4","audio":"004/004_100_017.mp3"},{"id":"13340","char_type":"word","text":"مُهَاجِرًا","aya":"100","sura":"4","audio":"004/004_100_018.mp3"},{"id":"13341","char_type":"word","text":"إِلَى","aya":"100","sura":"4","audio":"004/004_100_019.mp3"},{"id":"13342","char_type":"word","text":"اللَّهِ","aya":"100","sura":"4","audio":"004/004_100_020.mp3"},{"id":"13343","char_type":"word","text":"وَرَسُولِهِ","aya":"100","sura":"4","audio":"004/004_100_021.mp3"},{"id":"13344","char_type":"word","text":"ثُمَّ","aya":"100","sura":"4","audio":"004/004_100_022.mp3"},{"id":"13345","char_type":"word","text":"يُدْرِكْهُ","aya":"100","sura":"4","audio":"004/004_100_023.mp3"},{"id":"13346","char_type":"word","text":"الْمَوْتُ","aya":"100","sura":"4","audio":"004/004_100_024.mp3"}],"lineId":1393},{"line":13,"type":"line","surahNumber":"4","surah":"النساء","index":null,"ayah":"100","text":[{"id":"13347","char_type":"word","text":"فَقَدْ","aya":"100","sura":"4","audio":"004/004_100_025.mp3"},{"id":"13348","char_type":"word","text":"وَقَعَ","aya":"100","sura":"4","audio":"004/004_100_026.mp3"},{"id":"13349","char_type":"word","text":"أَجْرُهُ","aya":"100","sura":"4","audio":"004/004_100_027.mp3"},{"id":"13350","char_type":"word","text":"عَلَى","aya":"100","sura":"4","audio":"004/004_100_028.mp3"},{"id":"13351","char_type":"word","text":"اللَّهِ","aya":"100","sura":"4","audio":"004/004_100_029.mp3"},{"id":"13352","char_type":"pause","text":"ۗ","aya":"100","sura":"4","audio":null},{"id":"13353","char_type":"word","text":"وَكَانَ","aya":"100","sura":"4","audio":"004/004_100_031.mp3"},{"id":"13354","char_type":"word","text":"اللَّهُ","aya":"100","sura":"4","audio":"004/004_100_032.mp3"},{"id":"13355","char_type":"word","text":"غَفُورًا","aya":"100","sura":"4","audio":"004/004_100_033.mp3"},{"id":"13356","char_type":"word","text":"رَحِيمًا","aya":"100","sura":"4","audio":"004/004_100_034.mp3"},{"id":"13357","char_type":"end","text":null,"aya":"100","sura":"4","audio":"004100.mp3"},{"id":"13358","char_type":"word","text":"وَإِذَا","aya":"101","sura":"4","audio":"004/004_101_001.mp3"},{"id":"13359","char_type":"word","text":"ضَرَبْتُمْ","aya":"101","sura":"4","audio":"004/004_101_002.mp3"}],"lineId":1394},{"line":14,"type":"line","surahNumber":"4","surah":"النساء","index":null,"ayah":"101","text":[{"id":"13360","char_type":"word","text":"فِي","aya":"101","sura":"4","audio":"004/004_101_003.mp3"},{"id":"13361","char_type":"word","text":"الْأَرْضِ","aya":"101","sura":"4","audio":"004/004_101_004.mp3"},{"id":"13362","char_type":"word","text":"فَلَيْسَ","aya":"101","sura":"4","audio":"004/004_101_005.mp3"},{"id":"13363","char_type":"word","text":"عَلَيْكُمْ","aya":"101","sura":"4","audio":"004/004_101_006.mp3"},{"id":"13364","char_type":"word","text":"جُنَاحٌ","aya":"101","sura":"4","audio":"004/004_101_007.mp3"},{"id":"13365","char_type":"word","text":"أَنْ","aya":"101","sura":"4","audio":"004/004_101_008.mp3"},{"id":"13366","char_type":"word","text":"تَقْصُرُوا","aya":"101","sura":"4","audio":"004/004_101_009.mp3"},{"id":"13367","char_type":"word","text":"مِنَ","aya":"101","sura":"4","audio":"004/004_101_010.mp3"},{"id":"13368","char_type":"word","text":"الصَّلَاةِ","aya":"101","sura":"4","audio":"004/004_101_011.mp3"},{"id":"13369","char_type":"word","text":"إِنْ","aya":"101","sura":"4","audio":"004/004_101_012.mp3"},{"id":"13370","char_type":"word","text":"خِفْتُمْ","aya":"101","sura":"4","audio":"004/004_101_013.mp3"}],"lineId":1395},{"line":15,"type":"line","surahNumber":"4","surah":"النساء","index":null,"ayah":"101","text":[{"id":"13371","char_type":"word","text":"أَنْ","aya":"101","sura":"4","audio":"004/004_101_014.mp3"},{"id":"13372","char_type":"word","text":"يَفْتِنَكُمُ","aya":"101","sura":"4","audio":"004/004_101_015.mp3"},{"id":"13373","char_type":"word","text":"الَّذِينَ","aya":"101","sura":"4","audio":"004/004_101_016.mp3"},{"id":"13374","char_type":"word","text":"كَفَرُوا","aya":"101","sura":"4","audio":"004/004_101_017.mp3"},{"id":"13375","char_type":"pause","text":"ۚ","aya":"101","sura":"4","audio":null},{"id":"13376","char_type":"word","text":"إِنَّ","aya":"101","sura":"4","audio":"004/004_101_019.mp3"},{"id":"13377","char_type":"word","text":"الْكَافِرِينَ","aya":"101","sura":"4","audio":"004/004_101_020.mp3"},{"id":"13378","char_type":"word","text":"كَانُوا","aya":"101","sura":"4","audio":"004/004_101_021.mp3"},{"id":"13379","char_type":"word","text":"لَكُمْ","aya":"101","sura":"4","audio":"004/004_101_022.mp3"},{"id":"13380","char_type":"word","text":"عَدُوًّا","aya":"101","sura":"4","audio":"004/004_101_023.mp3"},{"id":"13381","char_type":"word","text":"مُبِينًا","aya":"101","sura":"4","audio":"004/004_101_024.mp3"},{"id":"13382","char_type":"end","text":null,"aya":"101","sura":"4","audio":"004101.mp3"}],"lineId":1396}]